pulsar_request_response/__init__.py
pulsar_request_response/asyncWrapper.py
pulsar_request_response/consumer_helper.py
pulsar_request_response/helper.py
pulsar_request_response/kafkapacket_pb2.py
pulsar_request_response/packagewrapper_pb2.py
pulsar_request_response/producer_helper.py
pulsar_request_response/publishesMessage.py
pulsar_request_response/pulsarWorker.py
pulsar_request_response/workerDelegate.py
pulsar_request_response-0.1.5.dist-info/LICENCE
pulsar_request_response-0.1.5.dist-info/METADATA
pulsar_request_response-0.1.5.dist-info/WHEEL
pulsar_request_response-0.1.5.dist-info/top_level.txt
pulsar_request_response-0.1.5.dist-info/RECORD
