Metadata-Version: 2.1
Name: pulsar-request-response
Version: 0.1.5
Summary: Common python package
Home-page: https://gitee.com/starview/pulsar-request-response
Author: mengzengshan
Author-email: 378077287@qq.com
License: UNKNOWN
Platform: UNKNOWN
Classifier: Programming Language :: Python :: 3
Classifier: License :: OSI Approved :: MIT License
Classifier: Operating System :: OS Independent
Requires-Python: >=3.6
License-File: LICENCE
Requires-Dist: pulsar-client
Requires-Dist: protobuf
